petkit_api/__init__.py
petkit_api/constants.py
petkit_api/exceptions.py
petkit_api/model.py
petkit_api/petkit_client.py
petkit_api-0.1.6.dist-info/LICENSE
petkit_api-0.1.6.dist-info/METADATA
petkit_api-0.1.6.dist-info/WHEEL
petkit_api-0.1.6.dist-info/top_level.txt
petkit_api-0.1.6.dist-info/RECORD
