Metadata-Version: 2.1
Name: petkit_api
Version: 0.1.6
Summary: Python library for PetKit's API
Home-page: https://github.com/Jezza34000/petkit-api
Author: Jezza34000
Author-email: mail@me.org
Project-URL: Bug Reports, https://github.com/Jezza34000/petkit-api/issues
Project-URL: Source, https://github.com/Jezza34000/petkit-api
Keywords: petkit,eversweet 3 pro,feeder mini,d4,petkit feeder,petkit water fountain,freshelement solo,pura x,pura max,pura air,purobot,eversweet max,pura max 2,yumshare dual hopper
Classifier: Programming Language :: Python :: 3
Classifier: License :: OSI Approved :: MIT License
Classifier: Operating System :: OS Independent
Requires-Python: >=3.11
License-File: LICENSE
Requires-Dist: aiohttp>=3.8.1
Requires-Dist: tzlocal>=4.2
